pyjokers/__init__.py
pyjokers/pyjokers.py
pyjokers-0.2.0.dist-info/LICENSE
pyjokers-0.2.0.dist-info/METADATA
pyjokers-0.2.0.dist-info/WHEEL
pyjokers-0.2.0.dist-info/entry_points.txt
pyjokers-0.2.0.dist-info/top_level.txt
pyjokers-0.2.0.dist-info/RECORD
