Metadata-Version: 2.1
Name: pyjokers
Version: 0.2.0
Summary: A simple joke generator
Home-page: https://github.com/tianhukj/pyjokers
Author: tianhukj
Author-email: tianhukj@outlook.com
License: UNKNOWN
Platform: UNKNOWN
Classifier: Programming Language :: Python :: 3
Classifier: License :: OSI Approved :: MIT License
Classifier: Operating System :: OS Independent
Requires-Python: >=3.6
